scute/__init__.py
scute-1.0.3.dist-info/METADATA
scute-1.0.3.dist-info/RECORD
scute-1.0.3.dist-info/WHEEL
scute-1.0.3.dist-info/top_level.txt
