Metadata-Version: 2.1
Name: scute
Version: 1.0.3
Summary: A small Dependency Injection Container, ported from PHP's Pimple
Home-page: https://github.com/DrBenton/scute
Author: Olivier Philippon
Author-email: olivier@rougemine.com
License: MIT
Keywords: Dependency injection
Platform: UNKNOWN
Classifier: Development Status :: 4 - Beta
Classifier: Intended Audience :: Developers
Classifier: License :: OSI Approved :: MIT License
Classifier: Programming Language :: Python :: 3.6
Requires-Python: >=3.6
Provides-Extra: dev
Provides-Extra: test
Provides-Extra: dev
Provides-Extra: test
Requires-Dist: pytest; extra == 'test'
Requires-Dist: pylint; extra == 'test'
